anilist/__init__.py
anilist/async_client.py
anilist/sync_client.py
anilist/utils.py
anilist/queries/__init__.py
anilist/queries/_query_files/__init__.py
anilist/queries/_query_files/activity/__init__.py
anilist/queries/_query_files/activity/list_activity.graphql
anilist/queries/_query_files/activity/message_activity.graphql
anilist/queries/_query_files/activity/message_activity_sent.graphql
anilist/queries/_query_files/activity/text_activity.graphql
anilist/queries/_query_files/get/__init__.py
anilist/queries/_query_files/get/anime_get.graphql
anilist/queries/_query_files/get/character_get.graphql
anilist/queries/_query_files/get/list_get.graphql
anilist/queries/_query_files/get/list_get_anime.graphql
anilist/queries/_query_files/get/list_get_manga.graphql
anilist/queries/_query_files/get/list_item_get.graphql
anilist/queries/_query_files/get/manga_get.graphql
anilist/queries/_query_files/get/staff_get.graphql
anilist/queries/_query_files/get/user_get.graphql
anilist/queries/_query_files/search/__init__.py
anilist/queries/_query_files/search/anime_search.graphql
anilist/queries/_query_files/search/character_search.graphql
anilist/queries/_query_files/search/manga_search.graphql
anilist/queries/_query_files/search/staff_search.graphql
anilist/queries/_query_files/search/user_search.graphql
anilist/types/__init__.py
anilist/types/activity.py
anilist/types/anime.py
anilist/types/character.py
anilist/types/cover.py
anilist/types/date.py
anilist/types/favourites.py
anilist/types/image.py
anilist/types/manga.py
anilist/types/medialist.py
anilist/types/name.py
anilist/types/next_airing.py
anilist/types/page.py
anilist/types/score.py
anilist/types/season.py
anilist/types/staff.py
anilist/types/statistics.py
anilist/types/title.py
anilist/types/trailer.py
anilist/types/user.py
python_anilist-1.0.9.dist-info/LICENSE
python_anilist-1.0.9.dist-info/METADATA
python_anilist-1.0.9.dist-info/MIT.txt
python_anilist-1.0.9.dist-info/WHEEL
python_anilist-1.0.9.dist-info/top_level.txt
python_anilist-1.0.9.dist-info/RECORD
