Metadata-Version: 2.1
Name: python-anilist
Version: 1.0.9
Summary: A simple wrapper for AniList.
Home-page: https://github.com/AmanoTeam/python-anilist
Author: AmanoTeam
Author-email: contact@amanoteam.com
License: MIT
Platform: UNKNOWN
Classifier: Development Status :: 4 - Beta
Classifier: License :: OSI Approved :: MIT License
Classifier: Operating System :: OS Independent
Classifier: Framework :: AsyncIO
Classifier: Programming Language :: Python :: 3
Classifier: Programming Language :: Python :: 3.7
Classifier: Programming Language :: Python :: 3.8
Classifier: Programming Language :: Python :: 3.9
Classifier: Programming Language :: Python :: 3.10
Classifier: Programming Language :: Python :: 3 :: Only
Requires-Python: >=3.7
License-File: LICENSE
License-File: LICENSES/MIT.txt
Requires-Dist: httpx[http2] (>=0.14.0)
Provides-Extra: testing
Requires-Dist: pytest (>=6.2) ; extra == 'testing'
Requires-Dist: pytest-cov (>=2.12) ; extra == 'testing'
Requires-Dist: tox (>=3.24) ; extra == 'testing'
